casino/__init__.py
casino/abstract.py
casino/backflow.py
casino/cusp.py
casino/dmc.py
casino/gjastrow.py
casino/harmonics.py
casino/jastrow.py
casino/loggers.py
casino/mpi.py
casino/overload.py
casino/ppotential.py
casino/profiling.py
casino/pycasino.py
casino/sem.py
casino/slater.py
casino/vmc.py
casino/wfn.py
casino/readers/__init__.py
casino/readers/backflow.py
casino/readers/gjastrow.py
casino/readers/input.py
casino/readers/jastrow.py
casino/readers/mdet.py
casino/readers/orca_pp2casino.py
casino/readers/wfn.py
casino-0.2.0.dist-info/LICENSE
casino-0.2.0.dist-info/METADATA
casino-0.2.0.dist-info/WHEEL
casino-0.2.0.dist-info/entry_points.txt
casino-0.2.0.dist-info/top_level.txt
casino-0.2.0.dist-info/RECORD
