Metadata-Version: 2.1
Name: casino
Version: 0.2.0
Summary: Quantum Monte Carlo for electrons in real space
Author-email: Vladmir Konkov <Konjkov.VV@gmail.com>
Maintainer-email: Vladmir Konkov <Konjkov.VV@gmail.com>
License: MIT
Project-URL: repository, https://github.com/Konjkov/pycasino
Project-URL: documentation, https://konjkov.github.io/pycasino.github.io/
Classifier: Development Status :: 4 - Beta
Classifier: Environment :: Console
Classifier: Intended Audience :: Science/Research
Classifier: License :: OSI Approved :: MIT License
Classifier: Operating System :: POSIX :: Linux
Classifier: Topic :: Scientific/Engineering :: Chemistry
Classifier: Programming Language :: Python
Classifier: Programming Language :: Python :: 3.10
Classifier: Programming Language :: Python :: 3.11
Requires-Python: >=3.10
License-File: LICENSE
Requires-Dist: numba>=0.59.0
Requires-Dist: mpi4py>=3.1.0
Requires-Dist: pyblock>=0.6.0
Requires-Dist: numpy>=1.24.0
Requires-Dist: scipy>=1.10.0
Requires-Dist: sympy>=1.12.0
Requires-Dist: matplotlib>=3.6.0
Requires-Dist: pandas>=2.0.2
